{
  "main": {
    "id": "78e1c84ae8dbb7f5",
    "type": "split",
    "children": [
      {
        "id": "7a498086e6403261",
        "type": "tabs",
        "children": [
          {
            "id": "e83f9bb200abde1e",
            "type": "leaf",
            "state": {
              "type": "graph",
              "state": {}
            }
          },
          {
            "id": "72b78aff3ac7fbcf",
            "type": "leaf",
            "state": {
              "type": "markdown",
              "state": {
                "file": "AllCourses/Python3 - Deep Dive (Part 1 - Functional)_NOTES/Section_11/Section 11.md",
                "mode": "source",
                "source": false
              }
            }
          }
        ]
      }
    ],
    "direction": "vertical"
  },
  "left": {
    "id": "dff2755bb3ec8243",
    "type": "split",
    "children": [
      {
        "id": "6a96e90948897a06",
        "type": "tabs",
        "children": [
          {
            "id": "3714b309f9f2b8fa",
            "type": "leaf",
            "state": {
              "type": "file-explorer",
              "state": {
                "sortOrder": "alphabetical"
              }
            }
          },
          {
            "id": "d856053bc02380ba",
            "type": "leaf",
            "state": {
              "type": "search",
              "state": {
                "query": "",
                "matchingCase": false,
                "explainSearch": false,
                "collapseAll": false,
                "extraContext": false,
                "sortOrder": "alphabetical"
              }
            }
          },
          {
            "id": "f759eca9bbec95db",
            "type": "leaf",
            "state": {
              "type": "bookmarks",
              "state": {}
            }
          }
        ]
      }
    ],
    "direction": "horizontal",
    "width": 348.5
  },
  "right": {
    "id": "929e49fe15f6f3fa",
    "type": "split",
    "children": [
      {
        "id": "8736c8c5e810093e",
        "type": "tabs",
        "children": [
          {
            "id": "008e8349b5edd532",
            "type": "leaf",
            "state": {
              "type": "backlink",
              "state": {
                "collapseAll": false,
                "extraContext": false,
                "sortOrder": "alphabetical",
                "showSearch": false,
                "searchQuery": "",
                "backlinkCollapsed": false,
                "unlinkedCollapsed": true
              }
            }
          },
          {
            "id": "9da25c4a7b543ff0",
            "type": "leaf",
            "state": {
              "type": "outgoing-link",
              "state": {
                "linksCollapsed": false,
                "unlinkedCollapsed": true
              }
            }
          },
          {
            "id": "6f074e6777be64c3",
            "type": "leaf",
            "state": {
              "type": "tag",
              "state": {
                "sortOrder": "frequency",
                "useHierarchy": true
              }
            }
          },
          {
            "id": "a9633aa033027b1c",
            "type": "leaf",
            "state": {
              "type": "outline",
              "state": {}
            }
          }
        ],
        "currentTab": 3
      }
    ],
    "direction": "horizontal",
    "width": 300
  },
  "left-ribbon": {
    "hiddenItems": {
      "switcher:Open quick switcher": false,
      "graph:Open graph view": false,
      "canvas:Create new canvas": false,
      "daily-notes:Open today's daily note": false,
      "templates:Insert template": false,
      "command-palette:Open command palette": false
    }
  },
  "active": "e83f9bb200abde1e",
  "lastOpenFiles": [
    "AllCourses/Python3 - Deep Dive (Part 1 - Functional)_NOTES/Section_11/Section 11.md",
    "AllCourses/Python3 - Deep Dive (Part 1 - Functional)_NOTES/Section_11/Lecture/8. Sentinel Values for Parameter Defaults - Lecture.md",
    "AllCourses/Python3 - Deep Dive (Part 1 - Functional)_NOTES/Section_11/Lecture/7. Command Line Arguments - Lecture.md",
    "AllCourses/Python3 - Deep Dive (Part 1 - Functional)_NOTES/Section_11/Lecture/6. Don't Use args and kwargs Names Blindly -  Lecture.md",
    "AllCourses/Python3 - Deep Dive (Part 1 - Functional)_NOTES/Section_11/Lecture/5. Time code using 'timeit' - Lecture.md",
    "AllCourses/Python3 - Deep Dive (Part 1 - Functional)_NOTES/Section_11/Lecture/4. Random Samples - Lecture.md",
    "AllCourses/Python3 - Deep Dive (Part 1 - Functional)_NOTES/Section_11/Lecture/3. Random Choices - Lecture.md",
    "AllCourses/Python3 - Deep Dive (Part 1 - Functional)_NOTES/Section_11/Lecture/2. Random (Seeds) - Lecture.md",
    "AllCourses/Python3 - Deep Dive (Part 1 - Functional)_NOTES/Section_11/Lecture/1. Additional Resources - Lecture.md",
    "AllCourses/Python3 - Deep Dive (Part 1 - Functional)_NOTES/Section_11/Lecture",
    "AllCourses/Python3 - Deep Dive (Part 1 - Functional)_NOTES/Python3 - Deep Dive (Part 1 - Functional).md",
    "AllCourses/Python3 - Deep Dive (Part 1 - Functional)_NOTES/Section_10/Lecture/8. Python 3.6 (f Strings) - Lecture.md",
    "AllCourses/Python3 - Deep Dive (Part 1 - Functional)_NOTES/Section_10/Lecture/7. Python 3.6 (Preserved Order of kwargs and Named Tuple Application) - Lecture.md",
    "AllCourses/Python3 - Deep Dive (Part 1 - Functional)_NOTES/Section_10/Section 10.md",
    "AllCourses/Python3 - Deep Dive (Part 1 - Functional)_NOTES/Section_11",
    "AllCourses/Python3 - Deep Dive (Part 1 - Functional)_NOTES/Section_10/Lecture/6. Python 3.6 (Underscores in Numeric Literals) - Lecture.md",
    "AllCourses/Python3 - Deep Dive (Part 1 - Functional)_NOTES/Section_10/Lecture/5. Python 3.6 (Directory Ordering) - Lecture.md",
    "AllCourses/Python3 - Deep Dive (Part 1 - Functional)_NOTES/Section_10/Lecture/4. Python 3.6 Highlights - Lecture.md",
    "AllCourses/Python3 - Deep Dive (Part 1 - Functional)_NOTES/Section_10/Lecture/3. Python 3.8 & 3.7 - Lecture.md",
    "AllCourses/Python3 - Deep Dive (Part 1 - Functional)_NOTES/Section_9/Section 9.md",
    "AllCourses/Python3 - Deep Dive (Part 1 - Functional)_NOTES/Section_10/Lecture/1. Python 3.10 - Lecture.md",
    "AllCourses/Python3 - Deep Dive (Part 1 - Functional)_NOTES/Section_10/Lecture",
    "AllCourses/Python3 - Deep Dive (Part 1 - Functional)_NOTES/Section_10/Lecture/2. Python 3.9 - Lecture.md",
    "AllCourses/Python3 - Deep Dive (Part 1 - Functional)_NOTES/Section_10",
    "AllCourses/CS50 Harvard Python Course Notes/Try-except-else-pass.md",
    "AllCourses/CS50 Harvard Python Course Notes/Packages.md",
    "AllCourses/CS50 Harvard Python Course Notes/Random.md",
    "AllCourses/CS50 Harvard Python Course Notes/Slice.md",
    "AllCourses/CS50 Harvard Python Course Notes/matchCase.md",
    "AllCourses/CS50 Harvard Python Course Notes/Lists.md",
    "AllCourses",
    "AllCourses/Python3 - Deep Dive (Part 1 - Functional)_NOTES/Section_9/Center Notes",
    "PythonCourseNotes/Section_9/Application",
    "AllCourses/Python3 - Deep Dive (Part 1 - Functional)_NOTES/Section_9/Coding",
    "AllCourses/Python3 - Deep Dive (Part 1 - Functional)_NOTES/Section_9/Lecture",
    "AllCourses/Python3 - Deep Dive (Part 1 - Functional)_NOTES/Section_9",
    "Untitled.canvas"
  ]
}